[{"product_id":1,"subcategory_id":1,"product_name":"Apple MacBook Air M2","brand":"Apple","sku":"SKU-LAP-00001","price_usd":1694,"stock_quantity":465,"created_at":"2023-07-22","updated_at":"2025-02-17","category_id":1,"subcategory_name":"Laptops","category_name":"Electronics"},{"product_id":2,"subcategory_id":1,"product_name":"Apple MacBook Pro M3","brand":"Apple","sku":"SKU-LAP-00002","price_usd":1619,"stock_quantity":390,"created_at":"2022-11-18","updated_at":"2025-04-29","category_id":1,"subcategory_name":"Laptops","category_name":"Electronics"},{"product_id":3,"subcategory_id":1,"product_name":"Dell XPS 13","brand":"Dell","sku":"SKU-LAP-00003","price_usd":1700,"stock_quantity":468,"created_at":"2023-11-03","updated_at":"2025-02-05","category_id":1,"subcategory_name":"Laptops","category_name":"Electronics"},{"product_id":4,"subcategory_id":1,"product_name":"HP Spectre x360","brand":"HP","sku":"SKU-LAP-00004","price_usd":1591,"stock_quantity":183,"created_at":"2024-08-06","updated_at":"2025-02-07","category_id":1,"subcategory_name":"Laptops","category_name":"Electronics"},{"product_id":5,"subcategory_id":1,"product_name":"Lenovo ThinkPad X1","brand":"Lenovo","sku":"SKU-LAP-00005","price_usd":1182,"stock_quantity":264,"created_at":"2022-10-26","updated_at":"2025-09-07","category_id":1,"subcategory_name":"Laptops","category_name":"Electronics"},{"product_id":6,"subcategory_id":1,"product_name":"Asus ZenBook 14","brand":"Asus","sku":"SKU-LAP-00006","price_usd":2217,"stock_quantity":264,"created_at":"2024-06-27","updated_at":"2025-09-29","category_id":1,"subcategory_name":"Laptops","category_name":"Electronics"},{"product_id":7,"subcategory_id":1,"product_name":"Acer Swift 5","brand":"Acer","sku":"SKU-LAP-00007","price_usd":1552,"stock_quantity":483,"created_at":"2024-04-24","updated_at":"2025-09-06","category_id":1,"subcategory_name":"Laptops","category_name":"Electronics"},{"product_id":8,"subcategory_id":1,"product_name":"Microsoft Surface Laptop 5","brand":"Microsoft","sku":"SKU-LAP-00008","price_usd":2432,"stock_quantity":275,"created_at":"2024-01-05","updated_at":"2025-08-01","category_id":1,"subcategory_name":"Laptops","category_name":"Electronics"},{"product_id":9,"subcategory_id":1,"product_name":"Razer Blade Stealth 13","brand":"Razer","sku":"SKU-LAP-00009","price_usd":1346,"stock_quantity":420,"created_at":"2023-03-02","updated_at":"2025-08-02","category_id":1,"subcategory_name":"Laptops","category_name":"Electronics"},{"product_id":10,"subcategory_id":1,"product_name":"Samsung Galaxy Book3","brand":"Samsung","sku":"SKU-LAP-00010","price_usd":969,"stock_quantity":382,"created_at":"2023-01-16","updated_at":"2024-11-24","category_id":1,"subcategory_name":"Laptops","category_name":"Electronics"},{"product_id":11,"subcategory_id":2,"product_name":"Bowflex SelectTech 552","brand":"Bowflex","sku":"SKU-DUM-00011","price_usd":267,"stock_quantity":211,"created_at":"2023-11-29","updated_at":"2025-09-02","category_id":2,"subcategory_name":"Dumbbells","category_name":"Sports"},{"product_id":12,"subcategory_id":2,"product_name":"NordicTrack Adjustable Dumbbell","brand":"NordicTrack","sku":"SKU-DUM-00012","price_usd":270,"stock_quantity":1283,"created_at":"2024-02-12","updated_at":"2025-06-04","category_id":2,"subcategory_name":"Dumbbells","category_name":"Sports"},{"product_id":13,"subcategory_id":2,"product_name":"Amazon Basics Rubber Dumbbell","brand":"Amazon","sku":"SKU-DUM-00013","price_usd":142,"stock_quantity":1167,"created_at":"2024-05-12","updated_at":"2025-02-22","category_id":2,"subcategory_name":"Dumbbells","category_name":"Sports"},{"product_id":14,"subcategory_id":2,"product_name":"Rogue Fitness Dumbbell","brand":"Rogue","sku":"SKU-DUM-00014","price_usd":200,"stock_quantity":707,"created_at":"2023-10-14","updated_at":"2025-04-26","category_id":2,"subcategory_name":"Dumbbells","category_name":"Sports"},{"product_id":15,"subcategory_id":2,"product_name":"PowerBlock Sport 24","brand":"PowerBlock","sku":"SKU-DUM-00015","price_usd":102,"stock_quantity":213,"created_at":"2023-08-15","updated_at":"2025-09-08","category_id":2,"subcategory_name":"Dumbbells","category_name":"Sports"},{"product_id":16,"subcategory_id":2,"product_name":"CAP Barbell Hex Dumbbell","brand":"CAP","sku":"SKU-DUM-00016","price_usd":217,"stock_quantity":1403,"created_at":"2023-11-28","updated_at":"2025-04-24","category_id":2,"subcategory_name":"Dumbbells","category_name":"Sports"},{"product_id":17,"subcategory_id":2,"product_name":"Yes4All Adjustable Dumbbell","brand":"Yes4All","sku":"SKU-DUM-00017","price_usd":201,"stock_quantity":677,"created_at":"2024-04-09","updated_at":"2025-02-09","category_id":2,"subcategory_name":"Dumbbells","category_name":"Sports"},{"product_id":18,"subcategory_id":2,"product_name":"Core Fitness Adjustable Dumbbell","brand":"Core","sku":"SKU-DUM-00018","price_usd":278,"stock_quantity":1284,"created_at":"2023-12-09","updated_at":"2025-04-29","category_id":2,"subcategory_name":"Dumbbells","category_name":"Sports"},{"product_id":19,"subcategory_id":2,"product_name":"Ativafit Dumbbell Set","brand":"Ativafit","sku":"SKU-DUM-00019","price_usd":268,"stock_quantity":391,"created_at":"2024-08-16","updated_at":"2025-03-18","category_id":2,"subcategory_name":"Dumbbells","category_name":"Sports"},{"product_id":20,"subcategory_id":2,"product_name":"ProForm Adjustable Dumbbell","brand":"ProForm","sku":"SKU-DUM-00020","price_usd":277,"stock_quantity":769,"created_at":"2024-03-14","updated_at":"2024-12-27","category_id":2,"subcategory_name":"Dumbbells","category_name":"Sports"}]